{
  "id": 12174,
  "congress": 103,
  "bill_no": "HB06313",
  "bill_no_f": "",
  "session_no": "20-1RS-019",
  "significance": 21,
  "manual_status": "",
  "manual_status_order": "0.00",
  "nature": null,
  "author": "K094;L089;K043;H072;",
  "mother_bill_no": "",
  "mother_flag": null,
  "mother_status": "",
  "title_full": "AN ACT PROVIDING FOR THE FAIR USE OF SOCIAL MEDIA, ARTIFICIAL INTELLIGENCE, AND INTERNET TECHNOLOGY FOR THE HOLDING OF FREE, ORDERLY, HONEST, PEACEFUL, AND CREDIBLE ELECTIONS",
  "title_short": "",
  "abstract": "",
  "alias_name": "",
  "date_filed": "2025-11-24",
  "urgent": false,
  "urgent_date": null,
  "admin_bill": false,
  "admin_date": null,
  "archive_date": null,
  "archive_transmitted_date": null,
  "withdrawn_date": null,
  "retro_stat": null,
  "retro_order": null,
  "status": "Pending with the Committee on SUFFRAGE AND ELECTORAL REFORMS since 2025-11-26",
  "status_order": "4.00",
  "mstat_order": "0.00",
  "senate_report_no": "",
  "senate_bill": "",
  "senate_urgent": false,
  "senate_urgent_date": null,
  "senate_adopted_date": null,
  "house_date_transmitted": null,
  "house_date_record": null,
  "remarks": "",
  "file": "HB06313.pdf",
  "size": 354217,
  "congress_desc": "20th Congress",
  "significance_desc": "National",
  "nature_desc": null,
  "text_as_filed": "https://docs.congress.hrep.online/legisdocs/basic_20/HB06313.pdf",
  "url": "https://docs.congress.hrep.online",
  "folder": "20",
  "authors": [
    {
      "id": 13613,
      "date": "2025-11-24",
      "sequence_no": 1,
      "name": "VILLAFUERTE, MIGUEL LUIS R.",
      "name_code": "Villafuerte (M. L. R.)"
    },
    {
      "id": 13614,
      "date": "2025-11-24",
      "sequence_no": 2,
      "name": "VILLAFUERTE, VINCENZO RENATO LUIGI R.",
      "name_code": "Villafuerte (V. R. L. R.)"
    },
    {
      "id": 13615,
      "date": "2025-11-24",
      "sequence_no": 3,
      "name": "HORIBATA, TSUYOSHI ANTHONY \"HORI\" G.",
      "name_code": "Horibata"
    },
    {
      "id": 13616,
      "date": "2025-11-24",
      "sequence_no": 4,
      "name": "RIDON, TERRY L.",
      "name_code": "Ridon"
    }
  ],
  "coauthors": null,
  "coauthors_journal": null,
  "authors_final": null,
  "authors_final_list": null,
  "authors_committee_report": null,
  "first_reading": {
    "id": 6314,
    "congress": 103,
    "bill_no": "HB06313",
    "report": "",
    "comm_act": "",
    "referral": "0537",
    "ref_name": "SUFFRAGE AND ELECTORAL REFORMS",
    "sub_name": "",
    "recomm": "",
    "remarks": "",
    "date_read": "2025-11-26"
  },
  "second_reading": null,
  "third_reading": null,
  "republic_acts": null,
  "votes": null,
  "deliberation": null,
  "deliberation_committee": null,
  "republic_act": null,
  "committee_action": null,
  "withdrawal": null,
  "consolidated_bills": null,
  "substituted_bills": null,
  "principal_referral": [
    {
      "id": 241686,
      "congress": 19,
      "bill_no": "HB06313",
      "referral": "E504",
      "ref_flag": 1,
      "newres_flag": false,
      "submit_flag": false,
      "change_flag": false,
      "orig_ref": "",
      "journal_no": "",
      "sequence_no": "1.0",
      "committee": "INFORMATION AND COMMUNICATIONS TECHNOLOGY"
    }
  ],
  "secondary_referral": null,
  "previous_referral": null,
  "referrals": [
    {
      "id": 260403,
      "congress": 103,
      "bill_no": "HB06313",
      "referral": "0537",
      "ref_flag": 1,
      "newres_flag": false,
      "submit_flag": false,
      "change_flag": false,
      "orig_ref": "",
      "journal_no": "",
      "sequence_no": "1.0",
      "committee": "SUFFRAGE AND ELECTORAL REFORMS"
    }
  ],
  "mother_bills": null,
  "concom_members": null,
  "bill_type": "House Bill"
}